circuitpython_cirque_pinnacle.py
circuitpython_cirque_pinnacle-2.0.0.dist-info/licenses/LICENSE
circuitpython_cirque_pinnacle-2.0.0.dist-info/METADATA
circuitpython_cirque_pinnacle-2.0.0.dist-info/WHEEL
circuitpython_cirque_pinnacle-2.0.0.dist-info/top_level.txt
circuitpython_cirque_pinnacle-2.0.0.dist-info/RECORD
