Metadata-Version: 2.4
Name: circuitpython-cirque-pinnacle
Version: 2.0.0
Summary: A CircuitPython driver for Cirque Pinnacle (1CA027) touch controller used in Cirque Trackpads
Author-email: Brendan Doherty <2bndy5@gmail.com>
License: MIT
Project-URL: Documentation, https://circuitpython-cirque-pinnacle.readthedocs.io
Project-URL: Source, https://github.com/2bndy5/CircuitPython_Cirque_Pinnacle
Project-URL: Tracker, https://github.com/2bndy5/CircuitPython_Cirque_Pinnacle/issues
Keywords: blinka,circuitpython,raspberrypi,driver,Cirque,Pinnacle,touch,sensor,trackpad
Classifier: Development Status :: 3 - Alpha
Classifier: Intended Audience :: Developers
Classifier: Topic :: Software Development :: Libraries
Classifier: Topic :: System :: Hardware
Classifier: License :: OSI Approved :: MIT License
Classifier: Programming Language :: Python :: 3
Classifier: Programming Language :: Python :: 3.7
Classifier: Programming Language :: Python :: 3.8
Classifier: Programming Language :: Python :: 3.9
Classifier: Programming Language :: Python :: 3.10
Requires-Python: >=3.7
License-File: LICENSE
Requires-Dist: Adafruit-Blinka
Requires-Dist: adafruit-circuitpython-busdevice
Dynamic: license-file
